{
"type": "FeatureCollection",
"name": "geo_46_地域密着型特定施設入居者生活介護（軽費老人ホーム）",
"crs": { "type": "name", "properties": { "name": "urn:ogc:def:crs:OGC:1.3:CRS84" } },
"features": [
{ "type": "Feature", "properties": { "内容": "ケアハウスにじの郷小松原【地域密着型特定施設入居者生活介護（軽費老人ホーム）】鹿児島市小松原1丁目15-19", "url": "https://www.kaigokensaku.mhlw.go.jp/46/index.php?action_kouhyou_detail_004_kani=true&JigyosyoCd=4690100864-00&ServiceCd=362&Type=search", "url2": "http://nizinosato.com/" }, "geometry": { "type": "Point", "coordinates": [ 130.533566800000017, 31.5380484 ] } },
{ "type": "Feature", "properties": { "内容": "清谿園ケアハウスしゅうゆう【地域密着型特定施設入居者生活介護（軽費老人ホーム）】山田町3802番地1清谿園ケアハウスしゅうゆう", "url": "https://www.kaigokensaku.mhlw.go.jp/46/index.php?action_kouhyou_detail_004_kani=true&JigyosyoCd=4690100849-00&ServiceCd=362&Type=search", "url2": "http://www.seikeien.com" }, "geometry": { "type": "Point", "coordinates": [ 130.491664799999967, 31.5730332 ] } }
]
}
